chunkflow/chunk.py
chunkflow/flow.py
chunkflow-0.2.8.dist-info/LICENSE
chunkflow-0.2.8.dist-info/METADATA
chunkflow-0.2.8.dist-info/WHEEL
chunkflow-0.2.8.dist-info/entry_points.txt
chunkflow-0.2.8.dist-info/top_level.txt
chunkflow-0.2.8.dist-info/RECORD
