Metadata-Version: 2.1
Name: chunkflow
Version: 0.2.8
Summary: Large Scale 3d Convolution Net Inference
Home-page: https://github.com/seung-lab/chunkflow
Author: Jingpeng Wu
Author-email: jingpeng.wu@gmail.com
License: Apache License 2.0
Platform: UNKNOWN
Classifier: Programming Language :: Python :: 3
Classifier: License :: OSI Approved :: Apache Software License
Classifier: Operating System :: OS Independent
Requires-Dist: click
Requires-Dist: numpy
Requires-Dist: cloud-volume
Requires-Dist: scikit-image
Requires-Dist: boto3
Requires-Dist: h5py
Requires-Dist: tifffile
Requires-Dist: neuroglancer
Requires-Dist: tinybrain
Requires-Dist: zmesh
